odoo/addons/website_snippet_marginless_gallery/README.rst
odoo/addons/website_snippet_marginless_gallery/__init__.py
odoo/addons/website_snippet_marginless_gallery/__manifest__.py
odoo/addons/website_snippet_marginless_gallery/i18n/ca.po
odoo/addons/website_snippet_marginless_gallery/i18n/de.po
odoo/addons/website_snippet_marginless_gallery/i18n/es.po
odoo/addons/website_snippet_marginless_gallery/i18n/fr.po
odoo/addons/website_snippet_marginless_gallery/i18n/it.po
odoo/addons/website_snippet_marginless_gallery/i18n/pt_BR.po
odoo/addons/website_snippet_marginless_gallery/i18n/ru.po
odoo/addons/website_snippet_marginless_gallery/i18n/sl.po
odoo/addons/website_snippet_marginless_gallery/i18n/website_snippet_marginless_gallery.pot
odoo/addons/website_snippet_marginless_gallery/images/marginless_gallery.png
odoo/addons/website_snippet_marginless_gallery/readme/CONTRIBUTORS.rst
odoo/addons/website_snippet_marginless_gallery/readme/DESCRIPTION.rst
odoo/addons/website_snippet_marginless_gallery/readme/USAGE.rst
odoo/addons/website_snippet_marginless_gallery/static/description/icon.png
odoo/addons/website_snippet_marginless_gallery/static/description/icon.svg
odoo/addons/website_snippet_marginless_gallery/static/description/index.html
odoo/addons/website_snippet_marginless_gallery/static/description/s_website_marginless_gallery.png
odoo/addons/website_snippet_marginless_gallery/static/src/js/website_snippet_marginless_gallery.tour.js
odoo/addons/website_snippet_marginless_gallery/tests/__init__.py
odoo/addons/website_snippet_marginless_gallery/tests/test_ui.py
odoo/addons/website_snippet_marginless_gallery/views/assets.xml
odoo/addons/website_snippet_marginless_gallery/views/snippets.xml
odoo12_addon_website_snippet_marginless_gallery-12.0.1.0.0.99.dev16.dist-info/METADATA
odoo12_addon_website_snippet_marginless_gallery-12.0.1.0.0.99.dev16.dist-info/WHEEL
odoo12_addon_website_snippet_marginless_gallery-12.0.1.0.0.99.dev16.dist-info/top_level.txt
odoo12_addon_website_snippet_marginless_gallery-12.0.1.0.0.99.dev16.dist-info/RECORD
